{
  "1": {
    "query": "audience in theatre seats",
    "title": "Lecture Lecture",
    "license": "cc0",
    "creator": "cogdogblog",
    "source": "https://www.flickr.com/photos/37996646802@N01/6288971",
    "file": "https://live.staticflickr.com/7/6288971_713a12216a_b.jpg"
  },
  "2": {
    "query": "traveler luggage station rain",
    "title": "Central Railway Station, Ann Street, Brisbane, October 1926",
    "license": "pdm",
    "creator": "Queensland State Archives",
    "source": "https://www.flickr.com/photos/60455048@N02/18821464161",
    "file": "https://live.staticflickr.com/528/18821464161_25d6151bcd_b.jpg"
  },
  "3": {
    "query": "person thinking by clock",
    "title": "2012_03_09",
    "license": "cc0",
    "creator": "Dennis S. Hurd",
    "source": "https://www.flickr.com/photos/43296902@N00/6968141027",
    "file": "https://live.staticflickr.com/7036/6968141027_61071bfe52_b.jpg"
  },
  "4": {
    "query": "railway track in rain",
    "title": "Beginning to See the Light",
    "license": "cc0",
    "creator": "sjpowermac",
    "source": "https://www.flickr.com/photos/41890311@N06/45167600715",
    "file": "https://live.staticflickr.com/4888/45167600715_2cc8dc547a_b.jpg"
  },
  "5": {
    "query": "team reviewing documents office",
    "title": "Is it possible to zoom in? Office laptop, light, screen, power cord, adaptor, red back lit key board, silk wall hanging, Lakota Lhamo Ling, Washington, USA",
    "license": "cc0",
    "creator": "Wonderlane",
    "source": "https://www.flickr.com/photos/71401718@N00/30121713318",
    "file": "https://live.staticflickr.com/1800/30121713318_bbd17fa6e6_b.jpg"
  },
  "6": {
    "query": "candle light",
    "title": "ICLS Pinning and Candle Lighting Ceremony 2016",
    "license": "pdm",
    "creator": "leandro_credo16",
    "source": "https://www.flickr.com/photos/125204774@N07/26921769390",
    "file": "https://live.staticflickr.com/7592/26921769390_ef50d81182_b.jpg"
  },
  "7": {
    "query": "frustrated employee at desk",
    "title": "Do I Have To Sacrifce A Virgin To Install Windows Software?",
    "license": "cc0",
    "creator": "cogdogblog",
    "source": "https://www.flickr.com/photos/37996646802@N01/13586281",
    "file": "https://live.staticflickr.com/10/13586281_77ce82fa68_b.jpg"
  },
  "8": {
    "query": "railway tracks",
    "title": "Fettlers constructing railway track by hand with pick and shovels, c 1880",
    "license": "pdm",
    "creator": "Queensland State Archives",
    "source": "https://www.flickr.com/photos/60455048@N02/18818816805",
    "file": "https://live.staticflickr.com/8888/18818816805_47050e849e_b.jpg"
  },
  "9": {
    "query": "rainy window",
    "title": "rainy window...",
    "license": "pdm",
    "creator": "chraebs",
    "source": "https://www.flickr.com/photos/21464823@N07/6241997076",
    "file": "https://live.staticflickr.com/6039/6241997076_975d5b9d4a_b.jpg"
  },
  "10": {
    "query": "office meeting",
    "title": "PD&R 2018 HHS-HUD-USDA Central Office Meeting",
    "license": "pdm",
    "creator": "U.S. Dept. of Housing and Urban Development (HUD)",
    "source": "https://www.flickr.com/photos/41555360@N03/43437673730",
    "file": "https://live.staticflickr.com/1948/43437673730_f0d1194c46_b.jpg"
  },
  "11": {
    "query": "empty room open door",
    "title": "2009/365/86 Emptied Anticipation",
    "license": "cc0",
    "creator": "cogdogblog",
    "source": "https://www.flickr.com/photos/37996646802@N01/3390627393",
    "file": "https://live.staticflickr.com/3474/3390627393_a5254ac427_b.jpg"
  },
  "12": {
    "query": "business chart presentation",
    "title": "Secretary of State Hillary Clinton in New Zealand - the second day - Wellington and Christchurch, November 2010",
    "license": "pdm",
    "creator": "US Embassy New Zealand",
    "source": "https://www.flickr.com/photos/46907600@N02/5147409141",
    "file": "https://live.staticflickr.com/4015/5147409141_a3a2b5dd41_b.jpg"
  },
  "13": {
    "query": "calendar and phone desk",
    "title": "Some accessories on a white desk",
    "license": "cc0",
    "creator": "freestocks.org",
    "source": "https://www.flickr.com/photos/135396164@N05/33572876081",
    "file": "https://live.staticflickr.com/2837/33572876081_7618124453_b.jpg"
  },
  "14": {
    "query": "person deep in thought",
    "title": "the servant of god anna fulgida bartolacelli",
    "license": "pdm",
    "creator": "Saints and Blesseds",
    "source": "https://www.flickr.com/photos/146857093@N05/48359888991",
    "file": "https://live.staticflickr.com/65535/48359888991_a411860cba_b.jpg"
  },
  "15": {
    "query": "train station",
    "title": "2010.02 - 'Photo of a decorated Dutch train - rail-car at the train-station decorated with graffiti art, location at the Central Station in Amsterdam - geo-tagged free urban photo, in public domain / Commons; Fons Heijnsbroek, The Netherlands",
    "license": "cc0",
    "creator": "Amsterdam free photos & pictures of the Dutch city",
    "source": "https://www.flickr.com/photos/104736837@N03/27657675041",
    "file": "https://live.staticflickr.com/7356/27657675041_eac9f498a7_b.jpg"
  },
  "16": {
    "query": "laptop desk",
    "title": "Laptop Desk",
    "license": "cc0",
    "creator": "Liam McKay",
    "source": "https://stocksnap.io/photo/laptop-desk-T2VQ2QPA3R",
    "file": "https://cdn.stocksnap.io/img-thumbs/960w/T2VQ2QPA3R.jpg"
  },
  "17": {
    "query": "graduates on university steps",
    "title": "No Known Restrictions: Law graduating class at Howard University, Washington, D.C. ca. 1900 (LOC)",
    "license": "pdm",
    "creator": "pingnews.com",
    "source": "https://www.flickr.com/photos/39735679@N00/434443595",
    "file": "https://live.staticflickr.com/154/434443595_6b3945097b_b.jpg"
  },
  "18": {
    "query": "newspaper",
    "title": "Business Woman is reading Newspaper",
    "license": "cc0",
    "creator": "tranmautritam",
    "source": "https://www.flickr.com/photos/80309306@N05/36098321632",
    "file": "https://live.staticflickr.com/4302/36098321632_b5b68cf471_b.jpg"
  },
  "19": {
    "query": "stock chart",
    "title": "Trans-Europe Express",
    "license": "pdm",
    "creator": "sjpowermac",
    "source": "https://www.flickr.com/photos/41890311@N06/51796560233",
    "file": "https://live.staticflickr.com/65535/51796560233_1ea45177cb_b.jpg"
  },
  "20": {
    "query": "coffee shop",
    "title": "Postcard: Sage Brush Motel & Coffee Shop, Kamloops, BC, 1962",
    "license": "pdm",
    "creator": "blizzy63",
    "source": "https://www.flickr.com/photos/45379817@N08/7518893500",
    "file": "https://live.staticflickr.com/8023/7518893500_18818b0af9_b.jpg"
  },
  "21": {
    "query": "business meeting",
    "title": "2014. 2014 Chair Mike McWilliams leads the business meeting. Western International Forest Disease Work Conference (WIFDWC). Cedar City, Utah.",
    "license": "pdm",
    "creator": "USDA Forest Service",
    "source": "https://www.flickr.com/photos/151887236@N05/43162497790",
    "file": "https://live.staticflickr.com/1965/43162497790_567c14ec0d_b.jpg"
  },
  "22": {
    "query": "executives signing documents",
    "title": "20130911-OSEC-LSC-0013",
    "license": "pdm",
    "creator": "USDAgov",
    "source": "https://www.flickr.com/photos/41284017@N08/9726739882",
    "file": "https://live.staticflickr.com/2805/9726739882_9254e32ce5_b.jpg"
  },
  "23": {
    "query": "handshake business",
    "title": "HANDSHAKE 2016-07-18",
    "license": "cc0",
    "creator": "eu2016sk",
    "source": "https://www.flickr.com/photos/142675453@N02/28351920816",
    "file": "https://live.staticflickr.com/7464/28351920816_febb127ec4_b.jpg"
  },
  "24": {
    "query": "two people talking",
    "title": "We Are News!",
    "license": "cc0",
    "creator": "cogdogblog",
    "source": "https://www.flickr.com/photos/37996646802@N01/3098651263",
    "file": "https://live.staticflickr.com/3149/3098651263_3675f4791e_b.jpg"
  },
  "25": {
    "query": "exhausted traveler at airport",
    "title": "️eXploration 13 🌟Beaches of Dinard & Saint Malo 🌌City/Nature",
    "license": "cc0",
    "creator": "eXploration Etoile",
    "source": "https://www.flickr.com/photos/156182786@N06/28246075269",
    "file": "https://live.staticflickr.com/4609/28246075269_96fb5dd2ff_b.jpg"
  },
  "26": {
    "query": "photographer team in rain",
    "title": "170915-N-JI086-096",
    "license": "pdm",
    "creator": "CNE CNA C6F",
    "source": "https://www.flickr.com/photos/94966166@N02/36484338884",
    "file": "https://live.staticflickr.com/4361/36484338884_725017dc25_b.jpg"
  },
  "27": {
    "query": "tea cup",
    "title": "Tea Set (Tea Cup and Saucer) LACMA 67.1.7a-b (3 of 3)",
    "license": "pdm",
    "creator": "Fæ",
    "source": "https://www.flickr.com/photos/50398299@N08/16446246975",
    "file": "https://live.staticflickr.com/7396/16446246975_4a9d4c9784_b.jpg"
  },
  "28": {
    "query": "office desk",
    "title": "Person Sitting at Office Desk in Warehouse by Pillar",
    "license": "cc0",
    "creator": "Image Catalog",
    "source": "https://www.flickr.com/photos/132795455@N08/18019403462",
    "file": "https://live.staticflickr.com/5470/18019403462_8fe0629a8d_b.jpg"
  },
  "29": {
    "query": "panel discussion microphone",
    "title": "Aaron Lemke (Unello Design) discussing at indie dev panel at SVVR (microphone at mouth looking stage left)",
    "license": "cc0",
    "creator": "D Coetzee",
    "source": "https://www.flickr.com/photos/29507259@N02/14090871598",
    "file": "https://live.staticflickr.com/2907/14090871598_9c00000c12_b.jpg"
  },
  "30": {
    "query": "bike lane city street",
    "title": "Carril bici",
    "license": "cc0",
    "creator": "Daquella manera",
    "source": "https://www.flickr.com/photos/62518311@N00/194452624",
    "file": "https://live.staticflickr.com/71/194452624_e0fc375fcd_b.jpg"
  }
}